odoo8_addon_analytic_partner_hr_timesheet_invoice-8.0.1.0.0.99.dev10-py2.7-nspkg.pth
odoo8_addon_analytic_partner_hr_timesheet_invoice-8.0.1.0.0.99.dev10.dist-info/DESCRIPTION.rst
odoo8_addon_analytic_partner_hr_timesheet_invoice-8.0.1.0.0.99.dev10.dist-info/METADATA
odoo8_addon_analytic_partner_hr_timesheet_invoice-8.0.1.0.0.99.dev10.dist-info/RECORD
odoo8_addon_analytic_partner_hr_timesheet_invoice-8.0.1.0.0.99.dev10.dist-info/WHEEL
odoo8_addon_analytic_partner_hr_timesheet_invoice-8.0.1.0.0.99.dev10.dist-info/metadata.json
odoo8_addon_analytic_partner_hr_timesheet_invoice-8.0.1.0.0.99.dev10.dist-info/namespace_packages.txt
odoo8_addon_analytic_partner_hr_timesheet_invoice-8.0.1.0.0.99.dev10.dist-info/top_level.txt
odoo_addons/analytic_partner_hr_timesheet_invoice/README.rst
odoo_addons/analytic_partner_hr_timesheet_invoice/__init__.py
odoo_addons/analytic_partner_hr_timesheet_invoice/__openerp__.py
odoo_addons/analytic_partner_hr_timesheet_invoice/i18n/analytic_partner_hr_timesheet_invoice.pot
odoo_addons/analytic_partner_hr_timesheet_invoice/i18n/de.po
odoo_addons/analytic_partner_hr_timesheet_invoice/i18n/es.po
odoo_addons/analytic_partner_hr_timesheet_invoice/i18n/es_MX.po
odoo_addons/analytic_partner_hr_timesheet_invoice/i18n/fi.po
odoo_addons/analytic_partner_hr_timesheet_invoice/i18n/fr.po
odoo_addons/analytic_partner_hr_timesheet_invoice/i18n/pt.po
odoo_addons/analytic_partner_hr_timesheet_invoice/i18n/pt_BR.po
odoo_addons/analytic_partner_hr_timesheet_invoice/i18n/sl.po
odoo_addons/analytic_partner_hr_timesheet_invoice/models/__init__.py
odoo_addons/analytic_partner_hr_timesheet_invoice/models/account_analytic_line.py
odoo_addons/analytic_partner_hr_timesheet_invoice/static/description/icon.png
odoo_addons/analytic_partner_hr_timesheet_invoice/static/description/icon.svg
odoo_addons/analytic_partner_hr_timesheet_invoice/tests/__init__.py
odoo_addons/analytic_partner_hr_timesheet_invoice/tests/test_analytic_partner_hr_timesheet_invoice.py
